LUCI/LuciBayesian.py
LUCI/LuciErrors.py
LUCI/LuciFit (conflicted).py
LUCI/LuciFit.py
LUCI/LuciFunctions.py
LUCI/LuciPlotting.py
LUCI/LuciSim.py
LUCI/__init__.py
LUCI_package-0.0.2.dist-info/AUTHORS.rst
LUCI_package-0.0.2.dist-info/LICENSE
LUCI_package-0.0.2.dist-info/LICENSE.txt
LUCI_package-0.0.2.dist-info/METADATA
LUCI_package-0.0.2.dist-info/WHEEL
LUCI_package-0.0.2.dist-info/top_level.txt
LUCI_package-0.0.2.dist-info/RECORD
