Metadata-Version: 2.1
Name: LUCI-package
Version: 0.0.2
Summary: A data analysis pipeline for SITELLE data cubes
Home-page: https://github.com/crhea93/LUCI
Author: Carter Rhea
Author-email: carter.rhea@umontreal.ca
License: MIT
Project-URL: Documentation, https://crhea93.github.io/LUCI/index.html
Project-URL: Tracker, https://github.com/crhea93/LUCI/issues
Platform: UNKNOWN
Classifier: Programming Language :: Python :: 3
Classifier: License :: OSI Approved :: MIT License
Classifier: Operating System :: OS Independent
Requires-Python: >=3.6
License-File: LICENSE
License-File: LICENSE.txt
License-File: AUTHORS.rst
